{
  "exportedAt": "2026-04-23T12:00:00.000Z",
  "dataCount": 1000000,
  "formulaCount": 20,
  "formulas": [
    {"targil_id": 1, "targil": "a + b", "tnai": null, "targil_false": null},
    {"targil_id": 2, "targil": "c * 2", "tnai": null, "targil_false": null},
    {"targil_id": 3, "targil": "a - b", "tnai": null, "targil_false": null},
    {"targil_id": 4, "targil": "d / 4", "tnai": null, "targil_false": null},
    {"targil_id": 5, "targil": "8 * (a + b)", "tnai": null, "targil_false": null},
    {"targil_id": 6, "targil": "(c * c) + (d * d)", "tnai": null, "targil_false": null},
    {"targil_id": 7, "targil": "(a + b + c + d) / 4", "tnai": null, "targil_false": null},
    {"targil_id": 8, "targil": "(a * b) - (c / 2)", "tnai": null, "targil_false": null},
    {"targil_id": 9, "targil": "b * 2", "tnai": "a > 5", "targil_false": "b / 2"},
    {"targil_id": 10, "targil": "a + 1", "tnai": "b < 10", "targil_false": "d - 1"},
    {"targil_id": 11, "targil": "1", "tnai": "a == c", "targil_false": "0"},
    {"targil_id": 12, "targil": "(a + b) * 2", "tnai": "c > d", "targil_false": "(a + b) / 2"},
    {"targil_id": 13, "targil": "SQRT((a*a)+(b*b))", "tnai": null, "targil_false": null},
    {"targil_id": 14, "targil": "LOG(b+1)", "tnai": null, "targil_false": null},
    {"targil_id": 15, "targil": "ABS(d-b)", "tnai": null, "targil_false": null},
    {"targil_id": 16, "targil": "POWER(a,2) + POWER(b,2)", "tnai": null, "targil_false": null},
    {"targil_id": 17, "targil": "SQRT(ABS(c-d))", "tnai": null, "targil_false": null},
    {"targil_id": 18, "targil": "LOG(a+b+1)", "tnai": null, "targil_false": null},
    {"targil_id": 19, "targil": "SQRT(a*a + b*b)", "tnai": "c > 50", "targil_false": "LOG(c+1)"},
    {"targil_id": 20, "targil": "POWER(a,2)", "tnai": "a > b", "targil_false": "POWER(b,2)"}
  ],
  "logs": [
    {"log_id": 1, "targil_id": 1, "method": "SQLDynamic", "run_time": 8.2},
    {"log_id": 2, "targil_id": 2, "method": "SQLDynamic", "run_time": 7.8},
    {"log_id": 3, "targil_id": 3, "method": "SQLDynamic", "run_time": 8.1},
    {"log_id": 4, "targil_id": 4, "method": "SQLDynamic", "run_time": 7.5},
    {"log_id": 5, "targil_id": 5, "method": "SQLDynamic", "run_time": 9.2},
    {"log_id": 6, "targil_id": 6, "method": "SQLDynamic", "run_time": 10.1},
    {"log_id": 7, "targil_id": 7, "method": "SQLDynamic", "run_time": 8.8},
    {"log_id": 8, "targil_id": 8, "method": "SQLDynamic", "run_time": 9.5},
    {"log_id": 9, "targil_id": 9, "method": "SQLDynamic", "run_time": 11.2},
    {"log_id": 10, "targil_id": 10, "method": "SQLDynamic", "run_time": 10.8},
    {"log_id": 11, "targil_id": 11, "method": "SQLDynamic", "run_time": 9.1},
    {"log_id": 12, "targil_id": 12, "method": "SQLDynamic", "run_time": 10.5},
    {"log_id": 13, "targil_id": 13, "method": "SQLDynamic", "run_time": 12.3},
    {"log_id": 14, "targil_id": 14, "method": "SQLDynamic", "run_time": 11.8},
    {"log_id": 15, "targil_id": 15, "method": "SQLDynamic", "run_time": 10.2},
    {"log_id": 16, "targil_id": 16, "method": "SQLDynamic", "run_time": 13.1},
    {"log_id": 17, "targil_id": 17, "method": "SQLDynamic", "run_time": 11.5},
    {"log_id": 18, "targil_id": 18, "method": "SQLDynamic", "run_time": 10.9},
    {"log_id": 19, "targil_id": 19, "method": "SQLDynamic", "run_time": 14.2},
    {"log_id": 20, "targil_id": 20, "method": "SQLDynamic", "run_time": 13.8},

    {"log_id": 21, "targil_id": 1, "method": "Roslyn", "run_time": 15.3},
    {"log_id": 22, "targil_id": 2, "method": "Roslyn", "run_time": 14.8},
    {"log_id": 23, "targil_id": 3, "method": "Roslyn", "run_time": 15.1},
    {"log_id": 24, "targil_id": 4, "method": "Roslyn", "run_time": 14.2},
    {"log_id": 25, "targil_id": 5, "method": "Roslyn", "run_time": 16.5},
    {"log_id": 26, "targil_id": 6, "method": "Roslyn", "run_time": 18.2},
    {"log_id": 27, "targil_id": 7, "method": "Roslyn", "run_time": 15.9},
    {"log_id": 28, "targil_id": 8, "method": "Roslyn", "run_time": 17.1},
    {"log_id": 29, "targil_id": 9, "method": "Roslyn", "run_time": 19.8},
    {"log_id": 30, "targil_id": 10, "method": "Roslyn", "run_time": 18.5},
    {"log_id": 31, "targil_id": 11, "method": "Roslyn", "run_time": 16.2},
    {"log_id": 32, "targil_id": 12, "method": "Roslyn", "run_time": 18.9},
    {"log_id": 33, "targil_id": 13, "method": "Roslyn", "run_time": 21.5},
    {"log_id": 34, "targil_id": 14, "method": "Roslyn", "run_time": 20.2},
    {"log_id": 35, "targil_id": 15, "method": "Roslyn", "run_time": 17.8},
    {"log_id": 36, "targil_id": 16, "method": "Roslyn", "run_time": 22.8},
    {"log_id": 37, "targil_id": 17, "method": "Roslyn", "run_time": 19.5},
    {"log_id": 38, "targil_id": 18, "method": "Roslyn", "run_time": 18.8},
    {"log_id": 39, "targil_id": 19, "method": "Roslyn", "run_time": 24.1},
    {"log_id": 40, "targil_id": 20, "method": "Roslyn", "run_time": 23.2},

    {"log_id": 41, "targil_id": 1, "method": "PythonSymPy", "run_time": 12.1},
    {"log_id": 42, "targil_id": 2, "method": "PythonSymPy", "run_time": 11.5},
    {"log_id": 43, "targil_id": 3, "method": "PythonSymPy", "run_time": 12.0},
    {"log_id": 44, "targil_id": 4, "method": "PythonSymPy", "run_time": 11.2},
    {"log_id": 45, "targil_id": 5, "method": "PythonSymPy", "run_time": 13.8},
    {"log_id": 46, "targil_id": 6, "method": "PythonSymPy", "run_time": 15.2},
    {"log_id": 47, "targil_id": 7, "method": "PythonSymPy", "run_time": 12.9},
    {"log_id": 48, "targil_id": 8, "method": "PythonSymPy", "run_time": 14.2},
    {"log_id": 49, "targil_id": 9, "method": "PythonSymPy", "run_time": 16.5},
    {"log_id": 50, "targil_id": 10, "method": "PythonSymPy", "run_time": 15.8},
    {"log_id": 51, "targil_id": 11, "method": "PythonSymPy", "run_time": 13.5},
    {"log_id": 52, "targil_id": 12, "method": "PythonSymPy", "run_time": 15.9},
    {"log_id": 53, "targil_id": 13, "method": "PythonSymPy", "run_time": 18.2},
    {"log_id": 54, "targil_id": 14, "method": "PythonSymPy", "run_time": 17.1},
    {"log_id": 55, "targil_id": 15, "method": "PythonSymPy", "run_time": 14.8},
    {"log_id": 56, "targil_id": 16, "method": "PythonSymPy", "run_time": 19.5},
    {"log_id": 57, "targil_id": 17, "method": "PythonSymPy", "run_time": 16.8},
    {"log_id": 58, "targil_id": 18, "method": "PythonSymPy", "run_time": 15.5},
    {"log_id": 59, "targil_id": 19, "method": "PythonSymPy", "run_time": 21.2},
    {"log_id": 60, "targil_id": 20, "method": "PythonSymPy", "run_time": 20.1},

    {"log_id": 61, "targil_id": 1, "method": "AITranslated", "run_time": 18.5},
    {"log_id": 62, "targil_id": 2, "method": "AITranslated", "run_time": 17.8},
    {"log_id": 63, "targil_id": 3, "method": "AITranslated", "run_time": 18.2},
    {"log_id": 64, "targil_id": 4, "method": "AITranslated", "run_time": 17.1},
    {"log_id": 65, "targil_id": 5, "method": "AITranslated", "run_time": 19.8},
    {"log_id": 66, "targil_id": 6, "method": "AITranslated", "run_time": 21.5},
    {"log_id": 67, "targil_id": 7, "method": "AITranslated", "run_time": 18.9},
    {"log_id": 68, "targil_id": 8, "method": "AITranslated", "run_time": 20.2},
    {"log_id": 69, "targil_id": 9, "method": "AITranslated", "run_time": 23.1},
    {"log_id": 70, "targil_id": 10, "method": "AITranslated", "run_time": 22.1},
    {"log_id": 71, "targil_id": 11, "method": "AITranslated", "run_time": 19.5},
    {"log_id": 72, "targil_id": 12, "method": "AITranslated", "run_time": 22.5},
    {"log_id": 73, "targil_id": 13, "method": "AITranslated", "run_time": 25.8},
    {"log_id": 74, "targil_id": 14, "method": "AITranslated", "run_time": 24.2},
    {"log_id": 75, "targil_id": 15, "method": "AITranslated", "run_time": 21.1},
    {"log_id": 76, "targil_id": 16, "method": "AITranslated", "run_time": 27.2},
    {"log_id": 77, "targil_id": 17, "method": "AITranslated", "run_time": 23.5},
    {"log_id": 78, "targil_id": 18, "method": "AITranslated", "run_time": 22.1},
    {"log_id": 79, "targil_id": 19, "method": "AITranslated", "run_time": 28.5},
    {"log_id": 80, "targil_id": 20, "method": "AITranslated", "run_time": 27.8}
  ],
  "summary": {
    "SQLDynamic": {
      "avg": 10.36,
      "min": 7.5,
      "max": 14.2,
      "runs": 20,
      "total_ops": 20000000
    },
    "Roslyn": {
      "avg": 18.61,
      "min": 14.2,
      "max": 24.1,
      "runs": 20,
      "total_ops": 20000000
    },
    "PythonSymPy": {
      "avg": 15.39,
      "min": 11.2,
      "max": 21.2,
      "runs": 20,
      "total_ops": 20000000
    },
    "AITranslated": {
      "avg": 21.96,
      "min": 17.1,
      "max": 28.5,
      "runs": 20,
      "total_ops": 20000000
    }
  }
}
